timeguard-supplymaster/__init__.py
timeguard-supplymaster/client.py
timeguard-supplymaster/device.py
timeguard-supplymaster/program.py
timeguard-supplymaster/timeslot.py
timeguard_supplymaster/__init__.py
timeguard_supplymaster/client.py
timeguard_supplymaster/device.py
timeguard_supplymaster/mode.py
timeguard_supplymaster/program.py
timeguard_supplymaster/timeslot.py
timeguard_supplymaster-0.0.17.dist-info/LICENSE
timeguard_supplymaster-0.0.17.dist-info/METADATA
timeguard_supplymaster-0.0.17.dist-info/WHEEL
timeguard_supplymaster-0.0.17.dist-info/top_level.txt
timeguard_supplymaster-0.0.17.dist-info/RECORD
