Metadata-Version: 2.1
Name: timeguard-supplymaster
Version: 0.0.17
Summary: Implementation of the API used by the Timeguard's Supplymaster application
Home-page: https://github.com/rjpearce/timeguard-supplymaster-python
Author: Richard Pearce
Author-email: rjpearce23@gmail.com
License: UNKNOWN
Platform: UNKNOWN
Classifier: Development Status :: 3 - Alpha
Classifier: Programming Language :: Python :: 3
Classifier: License :: OSI Approved :: GNU General Public License v3 or later (GPLv3+)
Classifier: Operating System :: OS Independent
Classifier: Topic :: Home Automation
Requires-Python: >=3.6
